{"RPMvzeu7v1ljqbwoVz72sA==":"5b9f93a90d820_thumb900-900x2111.jpg","owvDYj/1wb9g7ezZ0W9ucQ==":"5bbb5b29c0051_thumb900-900x900.jpg","O/YfIlI8KU5zm2HLkI/AjA==":"5bbefb93461bb_thumb900-900x1592.jpg","8c3oBsChPq0DjlTYjwRjeA==":"5bc5fc3e53c8d_thumb900-900x1239.jpg","z1uixEYgFDb3s4YhCtEJhg==":"5bc46cc5bcae5_thumb900-900x599.jpg","rwWstfXjsnkSGfin6eFhYg==":"5bc600b264194_thumb900-900x1239.jpg","fAhVYETRuKyQuviTS3R3mw==":"5bce140a85303_thumb900-900x2588.jpg","V6rXeJ6soAT3HaTrflLJCg==":"5bd06f1eb1863_thumb900-900x900.jpg","BY0qzgDFBhaT+Wo8/DhE3g==":"5bdbfeae72cab_thumb900-900x636.jpg","IFTV7Oe7/1lGXm9lEOC8sQ==":"5be4e4bd97a2e_thumb900-900x598.jpg","PoheF4MDyrYLpSiEmHryUA==":"5be54881e479d_thumb900-900x1555.jpg","WAT3tAbWbiYsSnFq98pUbQ==":"5bf0399c1173b_thumb900-900x1219.jpg","jyZzcOC1maQtrM++lZtzAg==":"5c3c8f51505d6_thumb900-900x900.jpg","TCxQxE5uvYneVycO06m02w==":"a%20logo-1-76x121.png","zOeogDldHMaL8rxenm8cgg==":"5c3c3499eb5af_thumb900-900x610.jpg","xVmNKlPDZ2VV/onPuEbw8g==":"tafri-2000x1412.jpg","DEWSzJaK4VrWxV31paZ57g==":"secas-final_45041648272_o-2000x1320.jpg","Dh5E+GS83tXQG8mZpt7Ofg==":"missfits-2000x1414.jpg","m9kYf7cT0p2Jz8QNhi8p/A==":"home-clean_45089984161_o-780x624.jpg","71E/XvKmDQPHSchh/SNqkw==":"supplement_mockup-white-label_48008108782_o-2000x1414.jpg","wKMelpvOqjv6S/Y/B1aZ3w==":"t-shirt-680x680.png","4ZrmlaKzK3QZJz5vvrniiA==":"scan%20casino-917x653.png","+fZqnoMpM2CO383p7O9VoA==":"final-psd_30257919687_o-1080x805.jpg","mgIyRL6+0dMiXN+jqx9SbA==":"maternity%20socal-680x453.jpg","KEZkONpuC/eo5Nm1Vh0VpA==":"lehla%20noor-799x514.jpg","gctCU2pyzpcBquxzWUH8Kg==":"nini's-842x595.png","qwZb7wfJdOP0ISxlhXWF1Q==":"life-therapy-postcard-1163x1651.jpg","4ijnNFuHWt7gW0jaeY2lnA==":"magic%20owl%20books-992x595.png","GwoCSTwJzp0V7/ZTtwkGPA==":"nursery-jean_46107803222_o-1372x966.png","UB3fBK0q07aBzGWgtAwf1w==":"o-2000x1414.jpg","8j02d/lgb6QtRI+HUVTVDg==":"offshore_43255941224_o-1980x1584.jpg","dM090l8V6tRZAafwwFiS+w==":"onedrive_48008263832_o-1980x1320.jpg","3EzmCXJWz7NxO5TaiDcFcA==":"phinite-trifold-900x3140.jpg","IpFA/gDpkcSa5EWyMPyeAg==":"emerald_48008206707_o-1400x936.jpg","zbsKVJ7wB9H9jq+1D9v/Nw==":"strippd-1331x1331.jpg","vLxmz1fm1iQ6Z69VX7DdHQ==":"equilibre-flyer-front_43926150382_o-1350x1080.jpg","b5JO1Guj/VKH1ufLqXB91Q==":"eye-optics---logo---business-cards_42165763990_o-2000x1250.jpg","eIiCOMSdvjp17oi5rMRlPQ==":"f4408b79599217516f6f054fabbb7797-2000x1414.jpg","a1Qc/PErCMuZUDL/+pfZEg==":"sled-night-2017-1530x1980.jpg","0ZXyDIO5YjH1ma4JaMMi6Q==":"5c8b896ad2ca3_thumb900-1-900x2473.jpg","x6WcH+HxkTNYKS6eyHVVxw==":"5c35b2b41dffa_thumb900-1-900x1272.jpg","med4b98Jm9lFG3NcE/ALsQ==":"5c0508b7ea78b_thumb900-1-900x1138.jpg","kwnP94DtH/QgVDaDL0aYtg==":"5c58184acb367_thumb900-1-900x502.jpg","FeLtyGdXC+J+y0gu1E1sZA==":"5c333695cb252_thumb900-1-900x1406.jpg","0tSx5jt/tJ1cQMoB39/e2w==":"5cbdb3229639d_thumb900-1-900x1335.jpg","arwbRavoFtGUVwU6r7TyNQ==":"automaze_48153948036_o-1-1980x1749.jpg","2WBSYRCL+TgC6ceKUrN74A==":"5d6c58f4e230e_thumb900-1-900x506.jpg","FLn5+TIUZ23UdAsWSv7w4g==":"5d6c59e7e4ae3_thumb900-1-900x506.jpg","7Odkyf+uBLnWA2tYB5wxow==":"5d25f1ec6f427_thumb900-1-900x1120.jpg","7CXLTL1i/4iSB8CREqEz0w==":"5d42ea2bdebdd_thumb900-1-900x1306.jpg","7VU/1D2wPQX/mGVHrEC68A==":"5d259e6dcbd0a_thumb900-1-900x1738.jpg","23Iq0VpIxHhmoPM430qQnA==":"5ded074c355c7_thumb900-1-900x1033.jpg","8OKKOFt/dk+bxAJMfE+qpw==":"buzzhire_45147328822_o-1-1400x1120.jpg","DN4ar04h+NMVSulhxSSJSQ==":"bv-1-2000x1414.jpg","xY6+33AhThp8+Qm80KRFSQ==":"alfanar-first-ppt_32287091088_o-1-900x2077.jpg","+tYBwyX53mwQ+T1lEcqO/A==":"fiverr-bad--boujee_43383571370_o-1-2000x1333.jpg","c5hlYTwxIdKjRbey6xa1IQ==":"fur-baby-business-card_43974716611_o-1-780x605.jpg","Rsco/gj26d22RKLz6CUJVw==":"gig-final_30152457637_o-1-780x1000.jpg","Tzj4SHULqUzrzihDiYe6vQ==":"greenlight-1-1200x595.png","6MpvDciW/Yvk2NFBAgY/JQ==":"handy-man-logo_48008087336_o-1-2000x1500.jpg","BETHVxU2TwEqhgDGkA5PfQ==":"heat--eat-002_30257919617_o-1-2000x1414.jpg","dMKKPQQ9oTADKDqPxsigGA==":"hipno-1-1000x641.png","nZuLqE7Fd5MUoksrI4UY0A==":"stratton-dental-sticker-1-1980x1515.jpg","6Xj1+Y8fCw/y4tV4gHspaw==":"hunni_45041248452_o-1-780x597.jpg","IkQopvwJs5hLFNuFakJmmw==":"leagacy-1-1024x762.jpg","BBxMtToY0qu1jZoUQAR4/Q==":"sw-1-799x533.jpg","U+N256J6W4eqKxLUuGqzAA==":"t-shirt-1-680x341.jpg","h+p/blByxlBM9gDcbFEzDw==":"usa_48008272072_o-1-1980x1416.jpg","SGrgv7GlzV3qWTZD7dWrYg==":"usan_46107802382_o-1-900x605.jpg","qlv9PEqqziu6lrpamrSHDA==":"amitt%20logo-2-76x40.png","r0Rswr1eSAMwjfgH1h8Yag==":"amitt%20logo-02-2-232x122.png","Uh4DHltNBDahCv6pPE/Ycg==":"a-logo-1-76x121.png","D0zjU4jkRImrq4cTgk6xYA==":"a-logo-231x195.jpg","1G33J/1GzTffoa6HCB3Nlg==":"a-logo-144x121.jpg"}